odoo/addons/stock_move_delay_report/README.rst
odoo/addons/stock_move_delay_report/__init__.py
odoo/addons/stock_move_delay_report/__manifest__.py
odoo/addons/stock_move_delay_report/i18n/stock_move_delay_report.pot
odoo/addons/stock_move_delay_report/models/__init__.py
odoo/addons/stock_move_delay_report/models/stock_move.py
odoo/addons/stock_move_delay_report/readme/CONTRIBUTORS.rst
odoo/addons/stock_move_delay_report/readme/DESCRIPTION.rst
odoo/addons/stock_move_delay_report/readme/USAGE.rst
odoo/addons/stock_move_delay_report/report/__init__.py
odoo/addons/stock_move_delay_report/report/delay_report.py
odoo/addons/stock_move_delay_report/report/delay_report_views.xml
odoo/addons/stock_move_delay_report/security/ir.model.access.csv
odoo/addons/stock_move_delay_report/security/report_security.xml
odoo/addons/stock_move_delay_report/static/description/icon.png
odoo/addons/stock_move_delay_report/static/description/index.html
odoo13_addon_stock_move_delay_report-13.0.1.0.1.dev2.dist-info/METADATA
odoo13_addon_stock_move_delay_report-13.0.1.0.1.dev2.dist-info/WHEEL
odoo13_addon_stock_move_delay_report-13.0.1.0.1.dev2.dist-info/top_level.txt
odoo13_addon_stock_move_delay_report-13.0.1.0.1.dev2.dist-info/RECORD
